sam_utilities/__init__.py
sam_utilities/lists.py
sam_utilities/main.py
sam_utilities/maths.py
sam_utilities-0.1.0.dist-info/LICENSE
sam_utilities-0.1.0.dist-info/METADATA
sam_utilities-0.1.0.dist-info/WHEEL
sam_utilities-0.1.0.dist-info/top_level.txt
sam_utilities-0.1.0.dist-info/RECORD
