Metadata-Version: 2.1
Name: sam_utilities
Version: 0.1.0
Summary: Random python utility methods I've made for myself, but put together in a package. 
Author: Samuel Hulme
Project-URL: Homepage, https://github.com/ajh123/sam_utils
Project-URL: Issues, https://github.com/ajh123/sam_utils/issues
Project-URL: Documentation, https://minersonline.uk/sam_utilities
Requires-Python: >=3.8
License-File: LICENSE
